Metadata-Version: 1.1
Name: metapensiero.asyncio.transaction
Version: 0.7
Summary: Handle coroutines from synchronous functions or methods (like special methods)
Home-page: https://github.com/azazel75/metapensiero.asyncio.transaction
Author: Alberto Berti
Author-email: alberto@metapensiero.it
License: GPLv3+
Platform: UNKNOWN
Classifier: Development Status :: 4 - Beta
Classifier: Programming Language :: Python
Classifier: Programming Language :: Python :: 3
Classifier: Programming Language :: Python :: 3.4
Classifier: Programming Language :: Python :: 3.5
Classifier: Intended Audience :: Developers
Classifier: License :: OSI Approved :: GNU General Public License (GPL)
